gimmebio.ram_seq-0.1.1-py3.6-nspkg.pth
gimmebio/ram_seq/__init__.py
gimmebio/ram_seq/ram_seq.py
gimmebio/ram_seq/utils.py
gimmebio.ram_seq-0.1.1.dist-info/METADATA
gimmebio.ram_seq-0.1.1.dist-info/RECORD
gimmebio.ram_seq-0.1.1.dist-info/WHEEL
gimmebio.ram_seq-0.1.1.dist-info/namespace_packages.txt
gimmebio.ram_seq-0.1.1.dist-info/top_level.txt
